user_messages/__init__.py
user_messages/admin.py
user_messages/api.py
user_messages/apps.py
user_messages/context_processors.py
user_messages/models.py
user_messages/locale/de/LC_MESSAGES/django.mo
user_messages/locale/de/LC_MESSAGES/django.po
user_messages/migrations/0001_squashed_0003_alter_message_index_together_and_more.py
user_messages/migrations/__init__.py
django_user_messages-1.1.0.dist-info/LICENSE
django_user_messages-1.1.0.dist-info/METADATA
django_user_messages-1.1.0.dist-info/WHEEL
django_user_messages-1.1.0.dist-info/top_level.txt
django_user_messages-1.1.0.dist-info/RECORD
